MANIFEST.in
README.rst
conf.py
coverage.ini
setup.cfg
setup.py
setup_helpers.py
tox.ini
acr_aiosmtpd.egg-info/PKG-INFO
acr_aiosmtpd.egg-info/SOURCES.txt
acr_aiosmtpd.egg-info/dependency_links.txt
acr_aiosmtpd.egg-info/entry_points.txt
acr_aiosmtpd.egg-info/requires.txt
acr_aiosmtpd.egg-info/top_level.txt
aiosmtpd/__init__.py
aiosmtpd/__main__.py
aiosmtpd/controller.py
aiosmtpd/handlers.py
aiosmtpd/lmtp.py
aiosmtpd/main.py
aiosmtpd/smtp.py
aiosmtpd/docs/NEWS.rst
aiosmtpd/docs/__init__.py
aiosmtpd/docs/controller.rst
aiosmtpd/docs/intro.rst
aiosmtpd/docs/mailbox.rst
aiosmtpd/testing/__init__.py
aiosmtpd/testing/flake8.py
aiosmtpd/testing/nose.py
aiosmtpd/tests/__init__.py
aiosmtpd/tests/test_handlers.py
aiosmtpd/tests/test_lmtp.py
aiosmtpd/tests/test_main.py
aiosmtpd/tests/test_server.py
aiosmtpd/tests/test_smtp.py
examples/__init__.py
examples/client.py
examples/server.py